activations_plus/__init__.py
activations_plus/bent_identity/__init__.py
activations_plus/bent_identity/bent_identity_func.py
activations_plus/elish/__init__.py
activations_plus/elish/elish_func.py
activations_plus/entmax/__init__.py
activations_plus/entmax/entmax.py
activations_plus/entmax/entmax_func.py
activations_plus/maxout/__init__.py
activations_plus/maxout/maxout_func.py
activations_plus/soft_clipping/__init__.py
activations_plus/soft_clipping/soft_clipping_func.py
activations_plus/sparsemax/__init__.py
activations_plus/sparsemax/sparsemax.py
activations_plus/sparsemax/sparsemax_func.py
activations_plus/sparsemax/utils.py
activations_plus/srelu/__init__.py
activations_plus/srelu/srelu_func.py
activations_plus-0.1.1.dist-info/METADATA
activations_plus-0.1.1.dist-info/WHEEL
activations_plus-0.1.1.dist-info/licenses/AUTHORS.md
activations_plus-0.1.1.dist-info/licenses/LICENSE
activations_plus-0.1.1.dist-info/RECORD
